{
  "project_info": {
    "project_number": "559952657667",
    "project_id": "cargotracking-f1301",
    "storage_bucket": "cargotracking-f1301.firebasestorage.app"
  },
  "client": [
    {
      "client_info": {
        "mobilesdk_app_id": "1:559952657667:android:86238e82e2673327ce7d36",
        "android_client_info": {
          "package_name": "com.example.cargotracking"
        }
      },
      "oauth_client": [],
      "api_key": [
        {
          "current_key": "AIzaSyDley2fH-G1Ja9pivsLGvxrrPh9Am75S1E"
        }
      ],
      "services": {
        "appinvite_service": {
          "other_platform_oauth_client": []
        }
      }
    }
  ],
  "configuration_version": "1"
}